{
  "monitor": "DuomoMonitor",
  "timestamp": "2025-04-19T12:42:21.893183",
  "total_products": 11,
  "products": [
    {
      "name": "Balenciaga Monday Sneakers PRO",
      "url": "https://backendocean.ilduomo.it/sneakers/63225-balenciaga9110-white-black-grey.html",
      "price": "¥5,972.61",
      "inventory_status": [
        {
          "status": "available",
          "status_index": 1,
          "sizes": [
            "44",
            "45"
          ]
        }
      ]
    },
    {
      "name": "Balenciaga Pool Slide",
      "url": "https://backendocean.ilduomo.it/flats/63160-balenciaga1190-grey-white.html",
      "price": "¥2,357.61",
      "inventory_status": [
        {
          "status": "available",
          "status_index": 1,
          "sizes": [
            "41",
            "42",
            "43",
            "44",
            "45"
          ]
        }
      ]
    },
    {
      "name": "Balenciaga Runner",
      "url": "https://backendocean.ilduomo.it/sneakers/62867-balenciaga1474-grey-blue-orange.html",
      "price": "¥6,852.78",
      "inventory_status": [
        {
          "status": "available",
          "status_index": 1,
          "sizes": [
            "41",
            "42",
            "43",
            "44",
            "45"
          ]
        }
      ]
    },
    {
      "name": "Balenciaga Pool Slide",
      "url": "https://backendocean.ilduomo.it/sandals/62761-balenciaga1090-black-white.html",
      "price": "¥2,357.61",
      "inventory_status": [
        {
          "status": "available",
          "status_index": 1,
          "sizes": [
            "41",
            "42",
            "43",
            "44"
          ]
        }
      ]
    },
    {
      "name": "Balenciaga Runner 2 Sneakers",
      "url": "https://backendocean.ilduomo.it/sneakers/62122-balenciaga9402-white-blue-mix.html",
      "price": "¥6,475.56",
      "inventory_status": [
        {
          "status": "available",
          "status_index": 1,
          "sizes": [
            "41",
            "42",
            "43",
            "44",
            "45"
          ]
        }
      ]
    },
    {
      "name": "Balenciaga 3xl Sneakers",
      "url": "https://backendocean.ilduomo.it/sneakers/61048-balenciaga9237-white-grey-green-yel.html",
      "price": "¥7,041.39",
      "inventory_status": [
        {
          "status": "available",
          "status_index": 1,
          "sizes": [
            "41",
            "42",
            "43",
            "44",
            "45"
          ]
        }
      ]
    },
    {
      "name": "Balenciaga Alaska Slipper",
      "url": "https://backendocean.ilduomo.it/flats/61049-balenciaga2200-brown-white.html",
      "price": "¥3,740.74",
      "inventory_status": [
        {
          "status": "available",
          "status_index": 1,
          "sizes": [
            "41",
            "43"
          ]
        }
      ]
    },
    {
      "name": "Balenciaga 6XL Sneakers",
      "url": "https://backendocean.ilduomo.it/sneakers/60494-balenciaga1937-gry-whit-gren-fl-yel.html",
      "price": "¥6,915.65",
      "inventory_status": [
        {
          "status": "available",
          "status_index": 1,
          "sizes": [
            "43",
            "44"
          ]
        }
      ]
    },
    {
      "name": "Balenciaga Track Gradient Sneakers",
      "url": "https://backendocean.ilduomo.it/sneakers/56311-balenciaga1220-grey-taupe.html",
      "price": "¥6,255.52",
      "inventory_status": [
        {
          "status": "available",
          "status_index": 1,
          "sizes": [
            "43"
          ]
        }
      ]
    },
    {
      "name": "Balenciaga Pool Slide Logo Shoes",
      "url": "https://backendocean.ilduomo.it/flats/51394-balenciaga1006-black-white.html",
      "price": "¥2,389.04",
      "inventory_status": [
        {
          "status": "available",
          "status_index": 1,
          "sizes": [
            "41"
          ]
        }
      ]
    },
    {
      "name": "Balenciaga Sunday Mule",
      "url": "https://backendocean.ilduomo.it/flats/57930-balenciaga2090-beige-off-white.html",
      "price": "¥3,168.62",
      "inventory_status": [
        {
          "status": "available",
          "status_index": 1,
          "sizes": [
            "44"
          ]
        }
      ]
    }
  ]
}